pingtest/GetDNS.py
pingtest/GetGateway.py
pingtest/SetLogging.py
pingtest/SpeedTest.py
pingtest/TKPingTest.py
pingtest/TKPlotDownload.py
pingtest/TKPlotUpload.py
pingtest/TkDisplay.py
pingtest/TkRefresh.py
pingtest/TkTraceroute.py
pingtest/__init__.py
pingtest-0.2.0.dist-info/WHEEL
pingtest-0.2.0.dist-info/METADATA
pingtest-0.2.0.dist-info/RECORD
