Metadata-Version: 2.1
Name: pingtest
Version: 0.2.0
Summary: 
Author: Colin Boyd
Author-email: csboyd@hotmail.com
Requires-Python: >=3.8,<4.0
Classifier: Programming Language :: Python :: 3
Classifier: Programming Language :: Python :: 3.8
Requires-Dist: asyncio (>=3.4.3,<4.0.0)
Requires-Dist: command (>=0.1.0,<0.2.0)
Requires-Dist: matplotlib (>=3.1.3,<4.0.0)
Requires-Dist: mysql.connector (>=2.2.9,<3.0.0)
Requires-Dist: pandas (>=1.0.1,<2.0.0)
Requires-Dist: pymysql (>=0.9.3,<0.10.0)
Requires-Dist: sqlalchemy (>=1.3.13,<2.0.0)
